[
  {
    "id": "aeropress",
    "name": "AeroPress",
    "category": "immersion",
    "imgUrl": "/_brew_methods/aeropress/aeropress.webp",
    "capacity": 250,
    "links": [
      {
        "name": "AeroPress Coffee and Espresso Maker",
        "url": "https://amzn.to/3ccG6AE",
        "imgUrl": "/_brew_methods/aeropress/buy_device.jpg"
      },
      {
        "name": "Replacement Filter Packs, 700 Count",
        "url": "https://amzn.to/3uOeYhT",
        "imgUrl": "/_brew_methods/aeropress/buy_filters.jpg"
      },
      {
        "name": "The MESH: Reusable Metal Filter",
        "url": "https://amzn.to/3PLwwDx",
        "imgUrl": "/_brew_methods/aeropress/buy_mesh_filter.jpg"
      }
    ]
  },
  {
    "id": "hario-v60",
    "name": "Hario V60",
    "category": "percolation",
    "imgUrl": "/_brew_methods/hario-v60/hario-v60.webp",
    "capacity": 250,
    "links": [
      {
        "name": "Hario V60 Ceramic Coffee Dripper",
        "url": "https://amzn.to/3PvEWPc",
        "imgUrl": "/_brew_methods/hario-v60/buy_device.webp"
      },
      {
        "name": "Paper Coffee Filters, 40 Count",
        "url": "https://amzn.to/3o8mQae",
        "imgUrl": "/_brew_methods/hario-v60/buy_filters].jpg"
      },
      {
        "name": "Hario V60 Drip Coffee Scale and Timer",
        "url": "https://amzn.to/3PeWWgR",
        "imgUrl": "/_brew_methods/hario-v60/buy_scale.webp"
      }
    ]
  },
  {
    "id": "chemex",
    "name": "Chemex",
    "category": "percolation",
    "imgUrl": "/_brew_methods/chemex/chemex.webp",
    "links": [
      {
        "name": "Chemex Bonded Filters, Natural Square, 100 Count",
        "url": "https://amzn.to/3ASSXlU",
        "imgUrl": "/_brew_methods/chemex/buy_filters_bonded.jpg"
      },
      {
        "name": "Chemex Filters, Natural Square, 2 x 100 Count",
        "url": "https://amzn.to/3yKxJnz",
        "imgUrl": "/_brew_methods/chemex/buy_filters_natural.jpg"
      },
      {
        "name": "Chemex Filters, Classic, 100 Count",
        "url": "https://amzn.to/3PxDvjd",
        "imgUrl": "/_brew_methods/chemex/buy_filters_classic.jpg"
      },
      {
        "name": "Chemex Brewer, 3-cup",
        "url": "https://amzn.to/3yKxOHT",
        "imgUrl": "/_brew_methods/chemex/buy_device_3.jpg"
      },
      {
        "name": "Chemex Brewer, 6-cup",
        "url": "https://amzn.to/3cj1cgL",
        "imgUrl": "/_brew_methods/chemex/buy_device_6.jpg"
      },
      {
        "name": "Chemex Brewer, 8-cup",
        "url": "https://amzn.to/3aODDvZ",
        "imgUrl": "/_brew_methods/chemex/buy_device_8.jpg"
      },
      {
        "name": "Chemex Brewer, 10-cup",
        "url": "https://amzn.to/3OfJxDO",
        "imgUrl": "/_brew_methods/chemex/buy_device_10.jpg"
      }
    ]
  },
  {
    "id": "stagg-x",
    "name": "Stagg X",
    "category": "percolation",
    "imgUrl": "/_brew_methods/stagg-x/stagg-x.gif",
    "capacity": 350,
    "links": [
      {
        "name": "Fellow Stagg [X] Pour Over Coffee Dripper",
        "url": "https://amzn.to/3yzem0E",
        "imgUrl": "/_brew_methods/stagg-x/buy_device.jpg"
      },
      {
        "name": "Fellow Stagg [X] Pour-Over Coffee Maker Set",
        "url": "https://amzn.to/3PrroEf",
        "imgUrl": "/_brew_methods/stagg-x/buy_device_set.jpg"
      },
      {
        "name": "Hario V60 Paper Coffee Filters",
        "url": "https://amzn.to/3yJ32Pr",
        "imgUrl": "/_brew_methods/hario-v60/buy_filters.jpg"
      },
      {
        "name": "Fellow Ode Brew Grinder",
        "url": "https://amzn.to/3PqtcgP",
        "imgUrl": "/_brew_methods/stagg-x/buy_grinder.jpg"
      },
      {
        "name": "Fellow Stagg EKG Electric Gooseneck Kettle",
        "url": "https://amzn.to/3aFN3K8",
        "imgUrl": "/_brew_methods/stagg-x/buy_kettle.jpg"
      }
    ]
  }
]
